AnalysisTools/__init__.py
AnalysisTools/gsea.py
AnalysisTools/limma_de.py
AnalysisTools/pca.py
ExpressionTools/EsetPrep.py
ExpressionTools/__init__.py
ExpressionTools/helpers.py
ExpressionTools/pyEset.py
ExpressionTools/pyXset.py
VizTools/__init__.py
VizTools/bar.py
VizTools/dendrogram.py
VizTools/density.py
VizTools/dot_plot.py
VizTools/dott_plot.py
VizTools/heatmap.py
VizTools/helpers.py
VizTools/kmeans.py
VizTools/misc.py
VizTools/plot_pca.py
VizTools/plotly.py
VizTools/ridge_plot.py
VizTools/venn.py
VizTools/violin.py
VizTools/volcano.py
GeneXpress-0.0.1.dist-info/LICENSE.txt
GeneXpress-0.0.1.dist-info/METADATA
GeneXpress-0.0.1.dist-info/WHEEL
GeneXpress-0.0.1.dist-info/top_level.txt
GeneXpress-0.0.1.dist-info/RECORD
