Metadata-Version: 2.1
Name: GeneXpress
Version: 0.0.1
Summary: A unified set of analysis and visualization tools intended for gene expression studies in Python, and an interface to the R ExpressionSet.
Home-page: UNKNOWN
Author: Colton J. Garelli
Author-email: UNKNOWN
License: GNU Affero General Public License v3.0
Platform: UNKNOWN
